syncfin/__init__.py
syncfin/config.py
syncfin/intrinsic_value.py
syncfin/scrapper.py
syncfin/syncfin.py
syncfin/wf_client.py
syncfin-0.0.1.dist-info/LICENSE
syncfin-0.0.1.dist-info/METADATA
syncfin-0.0.1.dist-info/WHEEL
syncfin-0.0.1.dist-info/top_level.txt
syncfin-0.0.1.dist-info/RECORD
