Metadata-Version: 2.1
Name: syncfin
Version: 0.0.1
Summary: Synchronized Finance.
Home-page: https://github.com/gitvipin/syncfin
Author: Vipin Sharma
Author-email: sh.vipin@gmail.com
License: UNKNOWN
Platform: UNKNOWN
Classifier: Programming Language :: Python :: 3
Classifier: License :: OSI Approved :: BSD License
Classifier: Operating System :: OS Independent
